p9customtheme/__init__.py
p9customtheme/colors.py
p9customtheme/logging.py
p9customtheme/scales.py
p9customtheme/settings.py
p9customtheme/theme.py
p9customtheme/types.py
p9customtheme/utils.py
p9customtheme-0.1.1.dist-info/licenses/LICENSE
p9customtheme-0.1.1.dist-info/METADATA
p9customtheme-0.1.1.dist-info/WHEEL
p9customtheme-0.1.1.dist-info/top_level.txt
p9customtheme-0.1.1.dist-info/RECORD
