Metadata-Version: 2.4
Name: p9customtheme
Version: 0.1.1
Summary: My personal plotnine theme package.
Author-email: Paul Saary <github@paulsaary.de>
License-Expression: Apache-2.0
Project-URL: Homepage, https://github.com/openpaul/p9customtheme
Project-URL: Changelog, https://github.com/openpaul/p9customtheme/releases
Project-URL: Issues, https://github.com/openpaul/p9customtheme/issues
Project-URL: CI, https://github.com/openpaul/p9customtheme/actions
Requires-Python: >=3.10
License-File: LICENSE
Requires-Dist: click
Requires-Dist: plotnine~=0.15.0
Requires-Dist: polars>=1.0.0
Requires-Dist: pandas>=1.0.0
Provides-Extra: test
Requires-Dist: pytest; extra == "test"
Requires-Dist: polars; extra == "test"
Requires-Dist: pyarrow; extra == "test"
Requires-Dist: ruff; extra == "test"
Dynamic: license-file
